enum_compat.py
zeroconf.py
zeroconf_py2compat-0.19.17.dist-info/COPYING
zeroconf_py2compat-0.19.17.dist-info/METADATA
zeroconf_py2compat-0.19.17.dist-info/WHEEL
zeroconf_py2compat-0.19.17.dist-info/top_level.txt
zeroconf_py2compat-0.19.17.dist-info/RECORD
