Metadata-Version: 2.1
Name: zeroconf-py2compat
Version: 0.19.17
Summary: Pure Python Multicast DNS Service Discovery Library (Bonjour/Avahi compatible)
Home-page: https://github.com/learningequality/python-zeroconf
Author: Paul Scott-Murphy, William McBrine, Jakub Stasiak, Jamie Alexandre, Richard Tibbles
License: LGPL
Keywords: Bonjour,Avahi,Zeroconf,Multicast DNS,Service Discovery,mDNS
Platform: unix
Platform: linux
Platform: osx
Classifier: Development Status :: 3 - Alpha
Classifier: Intended Audience :: Developers
Classifier: Intended Audience :: System Administrators
Classifier: License :: OSI Approved :: GNU Lesser General Public License v2 (LGPLv2)
Classifier: Operating System :: POSIX
Classifier: Operating System :: POSIX :: Linux
Classifier: Operating System :: MacOS :: MacOS X
Classifier: Topic :: Software Development :: Libraries
Classifier: Programming Language :: Python
Classifier: Programming Language :: Python :: 2
Classifier: Programming Language :: Python :: 2.6
Classifier: Programming Language :: Python :: 2.7
Classifier: Programming Language :: Python :: 3
Classifier: Programming Language :: Python :: 3.3
Classifier: Programming Language :: Python :: 3.4
Classifier: Programming Language :: Python :: 3.5
Classifier: Programming Language :: Python :: 3.6
Classifier: Programming Language :: Python :: Implementation :: CPython
Classifier: Programming Language :: Python :: Implementation :: PyPy
License-File: COPYING
